{"NVDA": "bullish", "AAPL": "bullish", "MSFT": "bullish", "GOOGL": "bullish", "AVGO": "bullish", "AMD": "bearish", "TSM": "bullish", "INTC": "bullish", "META": "bullish", "CRM": "bullish", "ORCL": "bearish", "ADBE": "bearish", "CSCO": "bullish", "TXN": "bullish", "QCOM": "bearish", "MU": "bullish", "PLTR": "bearish", "AMAT": "bullish", "NOW": "bearish", "ANET": "bullish", "JPM": "bearish", "V": "bearish", "MA": "bearish", "BAC": "bearish", "GS": "bearish", "MS": "bullish", "AXP": "bearish", "C": "bullish", "WFC": "bullish", "PYPL": "bearish", "SCHW": "bullish", "BLK": "bearish", "SPGI": "bearish", "CME": "bullish", "COF": "bearish", "AMP": "bearish", "AFL": "bullish", "COIN": "bearish", "LLY": "bearish", "UNH": "bearish", "JNJ": "bullish", "ABT": "bearish", "MRK": "bearish", "ABBV": "bullish", "PFE": "bullish", "AMGN": "bearish", "GILD": "bullish", "ISRG": "bearish", "SYK": "bearish", "VRTX": "bullish", "AMZN": "bullish", "WMT": "bearish", "COST": "bearish", "HD": "bearish", "PG": "bearish", "KO": "bullish", "PEP": "bullish", "MCD": "bullish", "NKE": "bearish", "SBUX": "bullish", "TGT": "bearish", "LOW": "bearish", "TJX": "bearish", "MELI": "bullish", "XOM": "bullish", "CVX": "bullish", "CAT": "bullish", "GE": "bearish", "BA": "bearish", "UPS": "bearish", "UNP": "bullish", "HON": "bearish", "LMT": "bullish", "DE": "bullish", "FDX": "bullish", "COP": "bullish", "HAL": "bearish", "SLB": "bullish", "NEE": "bullish", "VLO": "bearish", "NFLX": "bullish", "DIS": "bearish", "VZ": "bullish", "T": "bullish", "TMUS": "bearish", "UBER": "bearish", "PLD": "bullish", "AMT": "bullish", "EQIX": "bullish", "ABNB": "bearish", "BKNG": "bullish", "TSLA": "bearish", "CMCSA": "bearish", "PM": "bullish", "WM": "bullish", "ECL": "bearish", "BTC-USD": "bullish", "ETH-USD": "bullish", "BMNR": "bullish", "SI=F": "bullish"}