{"NVDA": "bearish", "AAPL": "bearish", "MSFT": "bearish", "GOOGL": "bearish", "AVGO": "bearish", "AMD": "bearish", "TSM": "bearish", "INTC": "bearish", "META": "bearish", "CRM": "bearish", "ORCL": "bullish", "ADBE": "bearish", "CSCO": "bearish", "TXN": "bearish", "QCOM": "bearish", "MU": "bullish", "PLTR": "bearish", "AMAT": "bullish", "NOW": "bullish", "ANET": "bearish", "JPM": "bearish", "V": "bearish", "MA": "bearish", "BAC": "bearish", "GS": "bearish", "MS": "bearish", "AXP": "bearish", "C": "bearish", "WFC": "bearish", "PYPL": "bearish", "SCHW": "bearish", "BLK": "bearish", "SPGI": "bearish", "CME": "bearish", "COF": "bearish", "AMP": "bearish", "AFL": "bearish", "COIN": "bearish", "LLY": "bullish", "UNH": "bullish", "JNJ": "bullish", "ABT": "bullish", "MRK": "bullish", "ABBV": "bullish", "PFE": "bullish", "AMGN": "bearish", "GILD": "bearish", "ISRG": "bearish", "SYK": "bullish", "VRTX": "bullish", "AMZN": "bearish", "WMT": "bullish", "COST": "bullish", "HD": "bullish", "PG": "bullish", "KO": "bullish", "PEP": "bearish", "MCD": "bullish", "NKE": "bearish", "SBUX": "bearish", "TGT": "bearish", "LOW": "bullish", "TJX": "bullish", "MELI": "bearish", "XOM": "bearish", "CVX": "bearish", "CAT": "bullish", "GE": "bearish", "BA": "bullish", "UPS": "bearish", "UNP": "bullish", "HON": "bearish", "LMT": "bullish", "DE": "bullish", "FDX": "bearish", "COP": "bullish", "HAL": "bearish", "SLB": "bearish", "NEE": "bullish", "VLO": "bearish", "NFLX": "bearish", "DIS": "bearish", "VZ": "bullish", "T": "bullish", "TMUS": "bullish", "UBER": "bearish", "PLD": "bearish", "AMT": "bullish", "EQIX": "bullish", "ABNB": "bearish", "BKNG": "bearish", "TSLA": "bearish", "CMCSA": "bearish", "PM": "bullish", "WM": "bearish", "ECL": "bullish", "BTC-USD": "bullish", "ETH-USD": "bullish", "BMNR": "bullish", "SI=F": "bullish"}